{
	"configurations" : 
	[
		{
			"directories" : 
			[
				{
					"build" : ".",
					"childIndexes" : 
					[
						1,
						4
					],
					"hasInstallRule" : true,
					"jsonFile" : "directory-.-Debug-f5ebdc15457944623624.json",
					"minimumCMakeVersion" : 
					{
						"string" : "3.10"
					},
					"projectIndex" : 0,
					"source" : ".",
					"targetIndexes" : 
					[
						0
					]
				},
				{
					"build" : "lib/googletest",
					"childIndexes" : 
					[
						2
					],
					"hasInstallRule" : true,
					"jsonFile" : "directory-lib.googletest-Debug-f566c6626c443d7d0c98.json",
					"minimumCMakeVersion" : 
					{
						"string" : "3.13"
					},
					"parentIndex" : 0,
					"projectIndex" : 1,
					"source" : "lib/googletest"
				},
				{
					"build" : "lib/googletest/googlemock",
					"childIndexes" : 
					[
						3
					],
					"hasInstallRule" : true,
					"jsonFile" : "directory-lib.googletest.googlemock-Debug-641eec133bae64ab5873.json",
					"minimumCMakeVersion" : 
					{
						"string" : "3.13"
					},
					"parentIndex" : 1,
					"projectIndex" : 2,
					"source" : "lib/googletest/googlemock",
					"targetIndexes" : 
					[
						20,
						21
					]
				},
				{
					"build" : "lib/googletest/googletest",
					"hasInstallRule" : true,
					"jsonFile" : "directory-lib.googletest.googletest-Debug-e58b864b10e2957bceff.json",
					"minimumCMakeVersion" : 
					{
						"string" : "3.13"
					},
					"parentIndex" : 2,
					"projectIndex" : 3,
					"source" : "lib/googletest/googletest",
					"targetIndexes" : 
					[
						22,
						23
					]
				},
				{
					"build" : "lib/benchmark",
					"childIndexes" : 
					[
						5,
						6
					],
					"hasInstallRule" : true,
					"jsonFile" : "directory-lib.benchmark-Debug-d2ba5b1f663fa066fc8d.json",
					"minimumCMakeVersion" : 
					{
						"string" : "3.10"
					},
					"parentIndex" : 0,
					"projectIndex" : 4,
					"source" : "lib/benchmark"
				},
				{
					"build" : "lib/benchmark/src",
					"hasInstallRule" : true,
					"jsonFile" : "directory-lib.benchmark.src-Debug-38c5455a48dd261db6c2.json",
					"minimumCMakeVersion" : 
					{
						"string" : "3.10"
					},
					"parentIndex" : 4,
					"projectIndex" : 4,
					"source" : "lib/benchmark/src",
					"targetIndexes" : 
					[
						3,
						5
					]
				},
				{
					"build" : "lib/benchmark/test",
					"jsonFile" : "directory-lib.benchmark.test-Debug-65279811cd8c96b07fa8.json",
					"minimumCMakeVersion" : 
					{
						"string" : "3.10"
					},
					"parentIndex" : 4,
					"projectIndex" : 4,
					"source" : "lib/benchmark/test",
					"targetIndexes" : 
					[
						1,
						2,
						4,
						6,
						7,
						8,
						9,
						10,
						11,
						12,
						13,
						14,
						15,
						16,
						17,
						18,
						19,
						24,
						25,
						26,
						27,
						28,
						29,
						30,
						31,
						32,
						33,
						34,
						35,
						36,
						37,
						38,
						39,
						40,
						41,
						42,
						43,
						44,
						45,
						46,
						47
					]
				}
			],
			"name" : "Debug",
			"projects" : 
			[
				{
					"childIndexes" : 
					[
						1,
						4
					],
					"directoryIndexes" : 
					[
						0
					],
					"name" : "aed2324_p03",
					"targetIndexes" : 
					[
						0
					]
				},
				{
					"childIndexes" : 
					[
						2
					],
					"directoryIndexes" : 
					[
						1
					],
					"name" : "googletest-distribution",
					"parentIndex" : 0
				},
				{
					"childIndexes" : 
					[
						3
					],
					"directoryIndexes" : 
					[
						2
					],
					"name" : "gmock",
					"parentIndex" : 1,
					"targetIndexes" : 
					[
						20,
						21
					]
				},
				{
					"directoryIndexes" : 
					[
						3
					],
					"name" : "gtest",
					"parentIndex" : 2,
					"targetIndexes" : 
					[
						22,
						23
					]
				},
				{
					"directoryIndexes" : 
					[
						4,
						5,
						6
					],
					"name" : "benchmark",
					"parentIndex" : 0,
					"targetIndexes" : 
					[
						1,
						2,
						3,
						4,
						5,
						6,
						7,
						8,
						9,
						10,
						11,
						12,
						13,
						14,
						15,
						16,
						17,
						18,
						19,
						24,
						25,
						26,
						27,
						28,
						29,
						30,
						31,
						32,
						33,
						34,
						35,
						36,
						37,
						38,
						39,
						40,
						41,
						42,
						43,
						44,
						45,
						46,
						47
					]
				}
			],
			"targets" : 
			[
				{
					"directoryIndex" : 0,
					"id" : "aed2324_p03::@6890427a1f51a3e7e1df",
					"jsonFile" : "target-aed2324_p03-Debug-1eaafe7e910b204038b6.json",
					"name" : "aed2324_p03",
					"projectIndex" : 0
				},
				{
					"directoryIndex" : 6,
					"id" : "args_product_test::@ffc329ffbc60a487a66f",
					"jsonFile" : "target-args_product_test-Debug-fa1cbe283c62fbfd82db.json",
					"name" : "args_product_test",
					"projectIndex" : 4
				},
				{
					"directoryIndex" : 6,
					"id" : "basic_test::@ffc329ffbc60a487a66f",
					"jsonFile" : "target-basic_test-Debug-b7becf621a83aa950319.json",
					"name" : "basic_test",
					"projectIndex" : 4
				},
				{
					"directoryIndex" : 5,
					"id" : "benchmark::@263d5672d1776d77af40",
					"jsonFile" : "target-benchmark-Debug-862491950c0d9397deaf.json",
					"name" : "benchmark",
					"projectIndex" : 4
				},
				{
					"directoryIndex" : 6,
					"id" : "benchmark_gtest::@ffc329ffbc60a487a66f",
					"jsonFile" : "target-benchmark_gtest-Debug-19576251ad850f7285c0.json",
					"name" : "benchmark_gtest",
					"projectIndex" : 4
				},
				{
					"directoryIndex" : 5,
					"id" : "benchmark_main::@263d5672d1776d77af40",
					"jsonFile" : "target-benchmark_main-Debug-8807f26e883fc70b329b.json",
					"name" : "benchmark_main",
					"projectIndex" : 4
				},
				{
					"directoryIndex" : 6,
					"id" : "benchmark_min_time_flag_iters_test::@ffc329ffbc60a487a66f",
					"jsonFile" : "target-benchmark_min_time_flag_iters_test-Debug-ab9383faaaaff389fe95.json",
					"name" : "benchmark_min_time_flag_iters_test",
					"projectIndex" : 4
				},
				{
					"directoryIndex" : 6,
					"id" : "benchmark_min_time_flag_time_test::@ffc329ffbc60a487a66f",
					"jsonFile" : "target-benchmark_min_time_flag_time_test-Debug-e326cccdea0f42e1f7f4.json",
					"name" : "benchmark_min_time_flag_time_test",
					"projectIndex" : 4
				},
				{
					"directoryIndex" : 6,
					"id" : "benchmark_name_gtest::@ffc329ffbc60a487a66f",
					"jsonFile" : "target-benchmark_name_gtest-Debug-df927f34c74c401deb52.json",
					"name" : "benchmark_name_gtest",
					"projectIndex" : 4
				},
				{
					"directoryIndex" : 6,
					"id" : "benchmark_random_interleaving_gtest::@ffc329ffbc60a487a66f",
					"jsonFile" : "target-benchmark_random_interleaving_gtest-Debug-8f4d7e13ecad42cf8e6c.json",
					"name" : "benchmark_random_interleaving_gtest",
					"projectIndex" : 4
				},
				{
					"directoryIndex" : 6,
					"id" : "benchmark_setup_teardown_test::@ffc329ffbc60a487a66f",
					"jsonFile" : "target-benchmark_setup_teardown_test-Debug-9bfd413e742c2d41ff37.json",
					"name" : "benchmark_setup_teardown_test",
					"projectIndex" : 4
				},
				{
					"directoryIndex" : 6,
					"id" : "benchmark_test::@ffc329ffbc60a487a66f",
					"jsonFile" : "target-benchmark_test-Debug-cab260852e94b8d95fc4.json",
					"name" : "benchmark_test",
					"projectIndex" : 4
				},
				{
					"directoryIndex" : 6,
					"id" : "commandlineflags_gtest::@ffc329ffbc60a487a66f",
					"jsonFile" : "target-commandlineflags_gtest-Debug-150bb490ce61cf6e4a18.json",
					"name" : "commandlineflags_gtest",
					"projectIndex" : 4
				},
				{
					"directoryIndex" : 6,
					"id" : "complexity_test::@ffc329ffbc60a487a66f",
					"jsonFile" : "target-complexity_test-Debug-549550460399d21ac26d.json",
					"name" : "complexity_test",
					"projectIndex" : 4
				},
				{
					"directoryIndex" : 6,
					"id" : "cxx03_test::@ffc329ffbc60a487a66f",
					"jsonFile" : "target-cxx03_test-Debug-34f569f108c15e87ab40.json",
					"name" : "cxx03_test",
					"projectIndex" : 4
				},
				{
					"directoryIndex" : 6,
					"id" : "diagnostics_test::@ffc329ffbc60a487a66f",
					"jsonFile" : "target-diagnostics_test-Debug-a9146551a7212d0afd0e.json",
					"name" : "diagnostics_test",
					"projectIndex" : 4
				},
				{
					"directoryIndex" : 6,
					"id" : "display_aggregates_only_test::@ffc329ffbc60a487a66f",
					"jsonFile" : "target-display_aggregates_only_test-Debug-87c52d36453eff9bfe77.json",
					"name" : "display_aggregates_only_test",
					"projectIndex" : 4
				},
				{
					"directoryIndex" : 6,
					"id" : "donotoptimize_test::@ffc329ffbc60a487a66f",
					"jsonFile" : "target-donotoptimize_test-Debug-f1c4ef01d68a54a36ced.json",
					"name" : "donotoptimize_test",
					"projectIndex" : 4
				},
				{
					"directoryIndex" : 6,
					"id" : "filter_test::@ffc329ffbc60a487a66f",
					"jsonFile" : "target-filter_test-Debug-5ea8fdfa683a22c3637f.json",
					"name" : "filter_test",
					"projectIndex" : 4
				},
				{
					"directoryIndex" : 6,
					"id" : "fixture_test::@ffc329ffbc60a487a66f",
					"jsonFile" : "target-fixture_test-Debug-43d3362e18150c2d00e5.json",
					"name" : "fixture_test",
					"projectIndex" : 4
				},
				{
					"directoryIndex" : 2,
					"id" : "gmock::@7712283c01f504ef6d93",
					"jsonFile" : "target-gmock-Debug-8353890c485afe0fff39.json",
					"name" : "gmock",
					"projectIndex" : 2
				},
				{
					"directoryIndex" : 2,
					"id" : "gmock_main::@7712283c01f504ef6d93",
					"jsonFile" : "target-gmock_main-Debug-a96758240e9b9154b89f.json",
					"name" : "gmock_main",
					"projectIndex" : 2
				},
				{
					"directoryIndex" : 3,
					"id" : "gtest::@7e3677ed2a4dc8c8eb88",
					"jsonFile" : "target-gtest-Debug-b7ae38ab35e87ef4476a.json",
					"name" : "gtest",
					"projectIndex" : 3
				},
				{
					"directoryIndex" : 3,
					"id" : "gtest_main::@7e3677ed2a4dc8c8eb88",
					"jsonFile" : "target-gtest_main-Debug-20c26f24b6296f6c065b.json",
					"name" : "gtest_main",
					"projectIndex" : 3
				},
				{
					"directoryIndex" : 6,
					"id" : "internal_threading_test::@ffc329ffbc60a487a66f",
					"jsonFile" : "target-internal_threading_test-Debug-ebc2cded88e93393b516.json",
					"name" : "internal_threading_test",
					"projectIndex" : 4
				},
				{
					"directoryIndex" : 6,
					"id" : "link_main_test::@ffc329ffbc60a487a66f",
					"jsonFile" : "target-link_main_test-Debug-efdbfd42a1bbd7418e5b.json",
					"name" : "link_main_test",
					"projectIndex" : 4
				},
				{
					"directoryIndex" : 6,
					"id" : "map_test::@ffc329ffbc60a487a66f",
					"jsonFile" : "target-map_test-Debug-4136c838df4a94db1b1b.json",
					"name" : "map_test",
					"projectIndex" : 4
				},
				{
					"directoryIndex" : 6,
					"id" : "memory_manager_test::@ffc329ffbc60a487a66f",
					"jsonFile" : "target-memory_manager_test-Debug-e2bb418bce6f92880e50.json",
					"name" : "memory_manager_test",
					"projectIndex" : 4
				},
				{
					"directoryIndex" : 6,
					"id" : "min_time_parse_gtest::@ffc329ffbc60a487a66f",
					"jsonFile" : "target-min_time_parse_gtest-Debug-32c607a4d5cd9b239d74.json",
					"name" : "min_time_parse_gtest",
					"projectIndex" : 4
				},
				{
					"directoryIndex" : 6,
					"id" : "multiple_ranges_test::@ffc329ffbc60a487a66f",
					"jsonFile" : "target-multiple_ranges_test-Debug-612f215271619300ff5f.json",
					"name" : "multiple_ranges_test",
					"projectIndex" : 4
				},
				{
					"directoryIndex" : 6,
					"id" : "options_test::@ffc329ffbc60a487a66f",
					"jsonFile" : "target-options_test-Debug-f857bf0ad15dcdfaf968.json",
					"name" : "options_test",
					"projectIndex" : 4
				},
				{
					"directoryIndex" : 6,
					"id" : "output_test_helper::@ffc329ffbc60a487a66f",
					"jsonFile" : "target-output_test_helper-Debug-9793340d6f9ecf664414.json",
					"name" : "output_test_helper",
					"projectIndex" : 4
				},
				{
					"directoryIndex" : 6,
					"id" : "perf_counters_gtest::@ffc329ffbc60a487a66f",
					"jsonFile" : "target-perf_counters_gtest-Debug-296005c24a7e768e645e.json",
					"name" : "perf_counters_gtest",
					"projectIndex" : 4
				},
				{
					"directoryIndex" : 6,
					"id" : "perf_counters_test::@ffc329ffbc60a487a66f",
					"jsonFile" : "target-perf_counters_test-Debug-b1dfca3c5d13684a6078.json",
					"name" : "perf_counters_test",
					"projectIndex" : 4
				},
				{
					"directoryIndex" : 6,
					"id" : "register_benchmark_test::@ffc329ffbc60a487a66f",
					"jsonFile" : "target-register_benchmark_test-Debug-b24fc998bc73c4976ad8.json",
					"name" : "register_benchmark_test",
					"projectIndex" : 4
				},
				{
					"directoryIndex" : 6,
					"id" : "repetitions_test::@ffc329ffbc60a487a66f",
					"jsonFile" : "target-repetitions_test-Debug-33ea809e28f9a74e5965.json",
					"name" : "repetitions_test",
					"projectIndex" : 4
				},
				{
					"directoryIndex" : 6,
					"id" : "report_aggregates_only_test::@ffc329ffbc60a487a66f",
					"jsonFile" : "target-report_aggregates_only_test-Debug-a25da7577a8b99821b22.json",
					"name" : "report_aggregates_only_test",
					"projectIndex" : 4
				},
				{
					"directoryIndex" : 6,
					"id" : "reporter_output_test::@ffc329ffbc60a487a66f",
					"jsonFile" : "target-reporter_output_test-Debug-4294b27034d048cf8ba2.json",
					"name" : "reporter_output_test",
					"projectIndex" : 4
				},
				{
					"directoryIndex" : 6,
					"id" : "skip_with_error_test::@ffc329ffbc60a487a66f",
					"jsonFile" : "target-skip_with_error_test-Debug-4ddc816753a73d333192.json",
					"name" : "skip_with_error_test",
					"projectIndex" : 4
				},
				{
					"directoryIndex" : 6,
					"id" : "spec_arg_test::@ffc329ffbc60a487a66f",
					"jsonFile" : "target-spec_arg_test-Debug-8616a52b1ddb329d0833.json",
					"name" : "spec_arg_test",
					"projectIndex" : 4
				},
				{
					"directoryIndex" : 6,
					"id" : "spec_arg_verbosity_test::@ffc329ffbc60a487a66f",
					"jsonFile" : "target-spec_arg_verbosity_test-Debug-52dfb779ca5b84b8ebcc.json",
					"name" : "spec_arg_verbosity_test",
					"projectIndex" : 4
				},
				{
					"directoryIndex" : 6,
					"id" : "statistics_gtest::@ffc329ffbc60a487a66f",
					"jsonFile" : "target-statistics_gtest-Debug-cf551921d0aaead8df99.json",
					"name" : "statistics_gtest",
					"projectIndex" : 4
				},
				{
					"directoryIndex" : 6,
					"id" : "string_util_gtest::@ffc329ffbc60a487a66f",
					"jsonFile" : "target-string_util_gtest-Debug-ca37e7ff19c6b0243b31.json",
					"name" : "string_util_gtest",
					"projectIndex" : 4
				},
				{
					"directoryIndex" : 6,
					"id" : "templated_fixture_test::@ffc329ffbc60a487a66f",
					"jsonFile" : "target-templated_fixture_test-Debug-836fdb60c99475d1d65b.json",
					"name" : "templated_fixture_test",
					"projectIndex" : 4
				},
				{
					"directoryIndex" : 6,
					"id" : "time_unit_gtest::@ffc329ffbc60a487a66f",
					"jsonFile" : "target-time_unit_gtest-Debug-8fa081e39ed6682bba4e.json",
					"name" : "time_unit_gtest",
					"projectIndex" : 4
				},
				{
					"directoryIndex" : 6,
					"id" : "user_counters_tabular_test::@ffc329ffbc60a487a66f",
					"jsonFile" : "target-user_counters_tabular_test-Debug-90fdf4086f370001d020.json",
					"name" : "user_counters_tabular_test",
					"projectIndex" : 4
				},
				{
					"directoryIndex" : 6,
					"id" : "user_counters_test::@ffc329ffbc60a487a66f",
					"jsonFile" : "target-user_counters_test-Debug-9ef3f334993414d5d42e.json",
					"name" : "user_counters_test",
					"projectIndex" : 4
				},
				{
					"directoryIndex" : 6,
					"id" : "user_counters_thousands_test::@ffc329ffbc60a487a66f",
					"jsonFile" : "target-user_counters_thousands_test-Debug-14507286811f22525665.json",
					"name" : "user_counters_thousands_test",
					"projectIndex" : 4
				}
			]
		}
	],
	"kind" : "codemodel",
	"paths" : 
	{
		"build" : "/home/tiago/Desktop/FEUP/2Ano/1Semestre/AED/Pr\u00e1ticas/Exerc\u00edcios Resolvidos/P03/Files/cmake-build-debug",
		"source" : "/home/tiago/Desktop/FEUP/2Ano/1Semestre/AED/Pr\u00e1ticas/Exerc\u00edcios Resolvidos/P03/Files"
	},
	"version" : 
	{
		"major" : 2,
		"minor" : 5
	}
}
